MANIFEST.in
setup.py
insight_pyres.egg-info/PKG-INFO
insight_pyres.egg-info/SOURCES.txt
insight_pyres.egg-info/dependency_links.txt
insight_pyres.egg-info/entry_points.txt
insight_pyres.egg-info/requires.txt
insight_pyres.egg-info/top_level.txt
pyres/__init__.py
pyres/exceptions.py
pyres/extensions.py
pyres/horde.py
pyres/job.py
pyres/json_parser.py
pyres/scheduler.py
pyres/scripts.py
pyres/utils.py
pyres/worker.py
pyres/failure/__init__.py
pyres/failure/base.py
pyres/failure/mail.py
pyres/failure/multiple.py
pyres/failure/redis.py
resweb/__init__.py
resweb/server.py
resweb/views.py
resweb/media/idle.png
resweb/media/jquery-1.3.2.min.js
resweb/media/jquery.relatize_date.js
resweb/media/poll.png
resweb/media/ranger.js
resweb/media/reset.css
resweb/media/style.css
resweb/media/working.png
resweb/templates/delayed.mustache
resweb/templates/delayed_timestamp.mustache
resweb/templates/failed.mustache
resweb/templates/footer.mustache
resweb/templates/header.mustache
resweb/templates/overview.mustache
resweb/templates/queue.mustache
resweb/templates/queue_full.mustache
resweb/templates/queues.mustache
resweb/templates/stat.mustache
resweb/templates/stats.mustache
resweb/templates/worker.mustache
resweb/templates/workers.mustache
resweb/templates/working.mustache
resweb/templates/working_full.mustache